sqlalchemy_jsonio/__init__.py
sqlalchemy_jsonio/cli.py
sqlalchemy_jsonio/const.py
sqlalchemy_jsonio/core.py
sqlalchemy_jsonio/exceptions.py
sqlalchemy_jsonio/factory.py
sqlalchemy_jsonio/registry.py
sqlalchemy_jsonio/util.py
sqlalchemy_jsonio-0.1.0.dist-info/DESCRIPTION.rst
sqlalchemy_jsonio-0.1.0.dist-info/METADATA
sqlalchemy_jsonio-0.1.0.dist-info/RECORD
sqlalchemy_jsonio-0.1.0.dist-info/WHEEL
sqlalchemy_jsonio-0.1.0.dist-info/entry_points.txt
sqlalchemy_jsonio-0.1.0.dist-info/metadata.json
sqlalchemy_jsonio-0.1.0.dist-info/top_level.txt
