Metadata-Version: 2.0
Name: sqlalchemy-jsonio
Version: 0.1.0
Summary: Tool for conversion between SQLAlchemy entities and JSON format dictionaries. Includes validation using jsonschema.Also contains CLI to generate schemas.
Home-page: https://github.com/RiceKab/sqlalchemy-jsonio
Author: Kevin CY Tang
Author-email: kevin@cyborn.be
License: MIT
Keywords: sqlalchemy json jsonschema
Platform: UNKNOWN
Classifier: Development Status :: 3 - Alpha
Classifier: Intended Audience :: Developers
Classifier: Topic :: Utilities
Classifier: License :: OSI Approved :: MIT License
Classifier: Programming Language :: Python :: 2.7
Classifier: Programming Language :: Python :: 3
Requires-Dist: SQLAlchemy
Requires-Dist: click
Requires-Dist: jsonschema
